MANIFEST.in
setup.cfg
setup.py
tests/__init__.py
tests/__init__.pyc
tests/test_widget.py
tests/test_widget.pyc
tw/__init__.py
tw/__init__.pyc
tw.jsunit.egg-info/PKG-INFO
tw.jsunit.egg-info/SOURCES.txt
tw.jsunit.egg-info/dependency_links.txt
tw.jsunit.egg-info/entry_points.txt
tw.jsunit.egg-info/namespace_packages.txt
tw.jsunit.egg-info/not-zip-safe
tw.jsunit.egg-info/paster_plugins.txt
tw.jsunit.egg-info/requires.txt
tw.jsunit.egg-info/top_level.txt
tw/jsunit/__init__.py
tw/jsunit/__init__.pyc
tw/jsunit/base.py
tw/jsunit/base.pyc
tw/jsunit/release.py
tw/jsunit/runner.py
tw/jsunit/runner.pyc
tw/jsunit/samples.py
tw/jsunit/widgets.py
tw/jsunit/widgets.pyc
tw/jsunit/static/changelog.txt
tw/jsunit/static/jsUnitCore.js
tw/jsunit/static/jsUnitMockTimeout.js
tw/jsunit/static/jsUnitTestManager.js
tw/jsunit/static/jsUnitTestSuite.js
tw/jsunit/static/jsUnitTracer.js
tw/jsunit/static/jsUnitVersionCheck.js
tw/jsunit/static/readme.txt
tw/jsunit/static/testRunner.html
tw/jsunit/static/xbDebug.js
tw/jsunit/static/app/emptyPage.html
tw/jsunit/static/app/jsUnitCore.js
tw/jsunit/static/app/jsUnitMockTimeout.js
tw/jsunit/static/app/jsUnitTestManager.js
tw/jsunit/static/app/jsUnitTestSuite.js
tw/jsunit/static/app/jsUnitTracer.js
tw/jsunit/static/app/jsUnitVersionCheck.js
tw/jsunit/static/app/main-counts-errors.html
tw/jsunit/static/app/main-counts-failures.html
tw/jsunit/static/app/main-counts-runs.html
tw/jsunit/static/app/main-counts.html
tw/jsunit/static/app/main-data.html
tw/jsunit/static/app/main-errors.html
tw/jsunit/static/app/main-frame.html
tw/jsunit/static/app/main-loader.html
tw/jsunit/static/app/main-progress.html
tw/jsunit/static/app/main-results.html
tw/jsunit/static/app/main-status.html
tw/jsunit/static/app/testContainer.html
tw/jsunit/static/app/testContainerController.html
tw/jsunit/static/app/xbDebug.js
tw/jsunit/static/app/css/jsUnitStyle.css
tw/jsunit/static/app/css/readme
tw/jsunit/static/css/jsUnitStyle.css
tw/jsunit/static/images/green.gif
tw/jsunit/static/images/logo_jsunit.gif
tw/jsunit/static/images/powerby-transparent.gif
tw/jsunit/static/images/red.gif
tw/jsunit/static/licenses/JDOM_license.txt
tw/jsunit/static/licenses/Jetty_license.html
tw/jsunit/static/licenses/MPL-1.1.txt
tw/jsunit/static/licenses/gpl-2.txt
tw/jsunit/static/licenses/index.html
