Metadata-Version: 1.0
Name: tw.jsunit
Version: 0.8
Summary: 'Widget for Javascript Unit Testing'
Home-page: 'http://www.jsunit.net'
Author: 'Sanjiv SIngh'
Author-email: 'SinghSanjivK@gmail.com'
License: UNKNOWN
Keywords: tw
Platform: UNKNOWN
Classifier: Development Status :: 3 - Alpha
Classifier: Environment :: Web Environment
Classifier: Environment :: Web Environment :: ToscaWidgets
Classifier: Topic :: Software Development :: Libraries :: Python Modules
Classifier: Topic :: Software Development :: Widget Sets
Classifier: Intended Audience :: Developers
Classifier: Operating System :: OS Independent
Classifier: Programming Language :: Python
